tensorfn/__init__.py
tensorfn/nsml_wrapper.py
tensorfn/test_util.py
tensorfn/trainer.py
tensorfn/checker/__init__.py
tensorfn/checker/backend.py
tensorfn/checker/checker.py
tensorfn/checker/checker2.py
tensorfn/config/__init__.py
tensorfn/config/builder.py
tensorfn/config/checker.py
tensorfn/config/config.py
tensorfn/config/data.py
tensorfn/config/lr_scheduler.py
tensorfn/config/optimizer.py
tensorfn/data/__init__.py
tensorfn/data/batch.py
tensorfn/data/cluegen.py
tensorfn/data/grouped_sampler.py
tensorfn/data/lmdb_reader.py
tensorfn/data/s3reader.py
tensorfn/distributed/__init__.py
tensorfn/distributed/distributed.py
tensorfn/distributed/launch.py
tensorfn/nn/__init__.py
tensorfn/nn/dropblock.py
tensorfn/nn/interpolate_spline.py
tensorfn/nn/loss.py
tensorfn/nn/model_util.py
tensorfn/nn/carafe/__init__.py
tensorfn/nn/carafe/carafe.py
tensorfn/optim/__init__.py
tensorfn/optim/lamb.py
tensorfn/optim/lr_scheduler.py
tensorfn/optim/rmsprop_tf.py
tensorfn/util/__init__.py
tensorfn/util/config.py
tensorfn/util/ensure.py
tensorfn/util/lazy_extension.py
tensorfn/util/logger.py
tensorfn/vision/__init__.py
tensorfn/vision/autoaugment.py
tensorfn/vision/mix.py
tensorfn/vision/transforms.py
tensorfn-0.1.28.dist-info/LICENSE
tensorfn-0.1.28.dist-info/METADATA
tensorfn-0.1.28.dist-info/WHEEL
tensorfn-0.1.28.dist-info/top_level.txt
tensorfn-0.1.28.dist-info/RECORD
