Metadata-Version: 2.1
Name: tensorfn
Version: 0.1.28
Summary: Non-opionated utility library for PyTorch
Home-page: https://github.com/rosinality/tensorfn
Author: Kim Seonghyeon
Author-email: kim.seonghyeon@navercorp.com
License: MIT
License-File: LICENSE
Requires-Dist: torch (>=1.1)
Requires-Dist: pydantic (>=1.8)
Requires-Dist: pyhocon (>=0.3.54)
Requires-Dist: termcolor
Requires-Dist: tabulate
Requires-Dist: boto3
Requires-Dist: rich
